wexample_helpers_api-0.0.71.dist-info/METADATA
wexample_helpers_api-0.0.71.dist-info/WHEEL
wexample_helpers_api-0.0.71.dist-info/entry_points.txt
wexample_helpers_api/__init__.py
wexample_helpers_api/__pycache__/__init__.py
wexample_helpers_api/common/__init__.py
wexample_helpers_api/common/__pycache__/__init__.py
wexample_helpers_api/common/abstract_gateway.py
wexample_helpers_api/common/http_request_payload.py
wexample_helpers_api/const/__init__.py
wexample_helpers_api/const/__pycache__/__init__.py
wexample_helpers_api/const/http.py
wexample_helpers_api/demo/__init__.py
wexample_helpers_api/demo/demo_simple_gateway.py
wexample_helpers_api/enums/__init__.py
wexample_helpers_api/enums/__pycache__/__init__.py
wexample_helpers_api/enums/http.py
wexample_helpers_api/errors/__init__.py
wexample_helpers_api/errors/gateway_authentication_error.py
wexample_helpers_api/errors/gateway_connexion_error.py
wexample_helpers_api/py.typed
wexample_helpers_api-0.0.71.dist-info/RECORD
